{
	"configurations" : 
	[
		{
			"directories" : 
			[
				{
					"build" : ".",
					"jsonFile" : "directory-.-Debug-d0094a50bb2071803777.json",
					"minimumCMakeVersion" : 
					{
						"string" : "3.24"
					},
					"projectIndex" : 0,
					"source" : ".",
					"targetIndexes" : 
					[
						0,
						1
					]
				}
			],
			"name" : "Debug",
			"projects" : 
			[
				{
					"directoryIndexes" : 
					[
						0
					],
					"name" : "untitled",
					"targetIndexes" : 
					[
						0,
						1
					]
				}
			],
			"targets" : 
			[
				{
					"directoryIndex" : 0,
					"id" : "huinya::@6890427a1f51a3e7e1df",
					"jsonFile" : "target-huinya-Debug-b8627f67d6e1bd7867ee.json",
					"name" : "huinya",
					"projectIndex" : 0
				},
				{
					"directoryIndex" : 0,
					"id" : "main::@6890427a1f51a3e7e1df",
					"jsonFile" : "target-main-Debug-84330fb83354805ab41b.json",
					"name" : "main",
					"projectIndex" : 0
				}
			]
		}
	],
	"kind" : "codemodel",
	"paths" : 
	{
		"build" : "C:/GitHub/Laboratory-works/Lazakovich V/Lab7/cmake-build-debug",
		"source" : "C:/GitHub/Laboratory-works/Lazakovich V/Lab7"
	},
	"version" : 
	{
		"major" : 2,
		"minor" : 4
	}
}
